<?xml version="1.0" encoding="UTF-8"?>
<!DOCTYPE mapper PUBLIC "-//mybatis.org//DTD Mapper 3.0//EN"
						"http://mybatis.org/dtd/mybatis-3-mapper.dtd">
						
<mapper namespace="mapper.teacher">

	<!-- 강사 채널 생성 -->
	<insert id="teacherChannel" parameterType="com.kosta.openday.teacher.dto.TeacherChannelDTO">
		 <![CDATA[
		     insert into teacherChannel (tchcNum,tchcNickname,tchcIntro,tchcCarrer,tchcRegistDate,tchcFollwer,userId)
		     values( nextval(orderInfo_seq),#{tchcNickname},#{tchcIntro},#{tchcCarrer},curdate(),
		     		#{tchcFollwer},#{userId})
	     ]]>
	</insert>
	
	<!-- 아이디로 강사 채널 선택 -->
	<select id="selectteacherChannel" parameterType="String" resultType="com.kosta.openday.teacher.dto.TeacherChannelDTO">
		 <![CDATA[
		 	select * from teacher_channel where userId = #{userId}
	 	 ]]>
	</select>
	
	<!-- 강사 팔로우 sql -->
	<insert id="teacherFollwer" parameterType="com.kosta.openday.teacher.dto.TeacherFollowDTO">
		 <![CDATA[
		     insert into teacherFollwer (tchcNum,userId)values(#{tchcNum},#{userId})
	     ]]>
	</insert>
	
	<!-- 아이디로 팔로우한 강사채널들 선택 -->
	<select id="selectteacherFollwerList" resultType="com.kosta.openday.teacher.dto.TeacherFollowDTO">
		 <![CDATA[
		 	select * from teacherFollwer
	 	 ]]>
	</select>
	
	<!-- 클래스 등록(승인 후) -->
	<insert id="classEnrollemnt" parameterType="com.kosta.openday.teacher.dto.ScheduleDTO">
		 <![CDATA[
		     insert into schedule (scdNum,scdDate,scdLoc,scdUploadDate,clsId)
		     values( nextval(schedule_seq),#{scdDate},#{scdLoc},curdate(),#{clsId})
	     ]]>
	</insert>
	
	<!-- 스케쥴 불러오기 -->
	<select id="selectSchedule" parameterType="Integer" resultType="java.util.Map">
		 <![CDATA[
		 	select * from schedule s join oclass o ON s.clsId = o.clsId WHERE s.clsId=#{clsId};
	 	 ]]>
	</select>
</mapper>